{"events":[{"title":"An exotic trip!!!!","image":"https://th.bing.com/th/id/OIP.7mA3Soq-8stwNj6BXpLObQHaFj?pid=ImgDet&rs=1","date":"2023-03-16","description":"The world's best trip","id":"34d8bdc2-bf97-4065-9e5d-1258a2c91185"},{"title":"The beautiful Movie night","image":"https://th.bing.com/th/id/OIP.vu5c2KZBgHaK4cqB1cWL6wHaE8?pid=ImgDet&rs=1","date":"2023-02-28","description":"Top-notch event","id":"698b6156-dfb4-4e27-a4b5-cdc79ab21f5e"},{"title":"A sweet event","image":"https://www.visitqatar.qa/content/dam/visitqatar/img/events-calendar/events-main.jpg","date":"2022-09-13","description":"Terrific event I attended","id":"356861ff-e81d-468a-ad99-6113f84c9040"},{"id":"e1","title":"A dummy event","date":"2023-02-22","image":"https://blog.hubspot.de/hubfs/Germany/Blog_images/Optimize_Marketing%20Events%20DACH%202021.jpg","description":"Join this amazing event and connect with fellow developers."}]}